[
  {
    "chainId": 1996,
    "symbol": "wDMT",
    "name": "Wrapped DMT",
    "address": "0x754cDAd6f5821077d6915004Be2cE05f93d176f8",
    "logoURI": "BASE_URL/assets/dmt.png",
    "decimals": 18,
    "isWNative": true,
    "common": true,
    "defaultSwapOutput": true,
    "quote": "native"
  },
  {
    "chainId": 1996,
    "symbol": "USDC",
    "name": "USD Coin",
    "address": "0x13D675BC5e659b11CFA331594cF35A20815dCF02",
    "logoURI": "BASE_URL/assets/usdc.svg",
    "decimals": 6,
    "common": true,
    "defaultSwapInput": true,
    "quote": "stable"
  },
  {
    "chainId": 1996,
    "symbol": "wETH",
    "name": "Wrapped ETH",
    "address": "0xE01e3b20C5819cf919F7f1a2b4C18bBfd222F376",
    "logoURI": "BASE_URL/assets/weth.svg",
    "decimals": 18,
    "common": true,
    "quote": "other"
  },
  {
    "chainId": 1996,
    "symbol": "STANKO",
    "name": "stanko",
    "address": "0x9c2730eA529c70E901fbDaf3e15E110CA8701C61",
    "logoURI": "BASE_URL/assets/stanko.png",
    "decimals": 18,
    "quote": "other"
  },
  {
    "chainId": 1996,
    "symbol": "STAR",
    "name": "Beat The Allegations",
    "address": "0x3C84f959f4b8ca0c39847d02f936e13Fa8fC4Eb9",
    "logoURI": "BASE_URL/assets/star.png",
    "decimals": 18,
    "quote": "other"
  },
  {
    "chainId": 1996,
    "symbol": "EUGENE",
    "name": "EUGENE",
    "address": "0x619Ef22392A549C9638D170db8C985fD147fAC98",
    "logoURI": "BASE_URL/assets/eugene.png",
    "decimals": 18,
    "quote": "other"
  }
]
